cryptographic_estimators/__init__.py
cryptographic_estimators/base_algorithm.py
cryptographic_estimators/base_constants.py
cryptographic_estimators/base_estimator.py
cryptographic_estimators/base_problem.py
cryptographic_estimators/estimation_renderer.py
cryptographic_estimators/helper.py
cryptographic_estimators/BIKEEstimator/__init__.py
cryptographic_estimators/BIKEEstimator/bike_algorithm.py
cryptographic_estimators/BIKEEstimator/bike_constants.py
cryptographic_estimators/BIKEEstimator/bike_estimator.py
cryptographic_estimators/BIKEEstimator/bike_problem.py
cryptographic_estimators/BIKEEstimator/BIKEAlgorithms/__init__.py
cryptographic_estimators/BIKEEstimator/BIKEAlgorithms/sd_key_attack.py
cryptographic_estimators/BIKEEstimator/BIKEAlgorithms/sd_msg_attack.py
cryptographic_estimators/DummyEstimator/__init__.py
cryptographic_estimators/DummyEstimator/dummy_algorithm.py
cryptographic_estimators/DummyEstimator/dummy_estimator.py
cryptographic_estimators/DummyEstimator/dummy_problem.py
cryptographic_estimators/DummyEstimator/DummyAlgorithms/__init__.py
cryptographic_estimators/DummyEstimator/DummyAlgorithms/dummy_algorithm1.py
cryptographic_estimators/IFEstimator/__init__.py
cryptographic_estimators/IFEstimator/if_algorithm.py
cryptographic_estimators/IFEstimator/if_constants.py
cryptographic_estimators/IFEstimator/if_estimator.py
cryptographic_estimators/IFEstimator/if_helper.py
cryptographic_estimators/IFEstimator/if_problem.py
cryptographic_estimators/IFEstimator/IFAlgorithms/__init__.py
cryptographic_estimators/IFEstimator/IFAlgorithms/gnfs.py
cryptographic_estimators/IFEstimator/IFAlgorithms/lenstra.py
cryptographic_estimators/IFEstimator/IFAlgorithms/trialdivision.py
cryptographic_estimators/LEEstimator/__init__.py
cryptographic_estimators/LEEstimator/le_algorithm.py
cryptographic_estimators/LEEstimator/le_constants.py
cryptographic_estimators/LEEstimator/le_estimator.py
cryptographic_estimators/LEEstimator/le_helper.py
cryptographic_estimators-2.1.1.dist-info/licenses/LICENSE
cryptographic_estimators-2.1.1.dist-info/METADATA
cryptographic_estimators-2.1.1.dist-info/WHEEL
cryptographic_estimators-2.1.1.dist-info/top_level.txt
cryptographic_estimators-2.1.1.dist-info/RECORD
