Metadata-Version: 2.4
Name: cryptographic_estimators
Version: 2.1.1
Summary: This library provides bit security estimators and asymptotic complexity estimators for cryptographic problems.
Author-email: TII <cryptographic_estimators@tii.ae>
License-Expression: Apache-2.0
Project-URL: Homepage, https://estimators.crypto.tii.ae/
Project-URL: Documentation, https://github.com/Crypto-TII/CryptographicEstimators/blob/main/docs/github/user_guide.md
Project-URL: Repository, https://github.com/Crypto-TII/CryptographicEstimators
Project-URL: Issues, https://github.com/Crypto-TII/CryptographicEstimators/issues
Classifier: Programming Language :: Python :: 3
Classifier: Operating System :: OS Independent
Classifier: Topic :: Security :: Cryptography
License-File: LICENSE
Requires-Dist: setuptools>=45
Requires-Dist: sphinx>=5.3.0
Requires-Dist: scipy>=1.4.0
Requires-Dist: furo
Requires-Dist: prettytable
Requires-Dist: pytest
Requires-Dist: pytest-xdist
Requires-Dist: python-flint
Requires-Dist: pytest-cov
Requires-Dist: pyyaml
Requires-Dist: sympy
Dynamic: license-file
